prefect_alert/__init__.py
prefect_alert/_version.py
prefect_alert/alert.py
prefect_alert/utilities.py
prefect_alert-0.1.3.dist-info/LICENSE
prefect_alert-0.1.3.dist-info/METADATA
prefect_alert-0.1.3.dist-info/WHEEL
prefect_alert-0.1.3.dist-info/entry_points.txt
prefect_alert-0.1.3.dist-info/top_level.txt
prefect_alert-0.1.3.dist-info/RECORD
